passgent/__init__.py
passgent/passgent.py
passgent-0.3.0.dist-info/licenses/LICENSE
passgent-0.3.0.dist-info/METADATA
passgent-0.3.0.dist-info/WHEEL
passgent-0.3.0.dist-info/top_level.txt
passgent-0.3.0.dist-info/RECORD
