Metadata-Version: 2.4
Name: passgent
Version: 0.3.0
Summary: Password generator
Home-page: https://github.com/MrSanZz/passgent
Author: MrSanZz
Author-email: drownedmrsanzz@proton.me
Classifier: Programming Language :: Python :: 3
Classifier: License :: OSI Approved :: MIT License
Classifier: Operating System :: OS Independent
Requires-Python: >=3.6
License-File: LICENSE
Dynamic: author
Dynamic: author-email
Dynamic: classifier
Dynamic: description
Dynamic: description-content-type
Dynamic: home-page
Dynamic: license-file
Dynamic: requires-python
Dynamic: summary
